msaStorageDict
