Metadata-Version: 2.1
Name: msaStorageDict
Version: 0.0.3
Summary: Dict with a Storage Backend like redis or Zookeeper
Home-page: https://github.com/swelcker/msaStorageDict
Download-URL: http://pypi.python.org/pypi/msaStorageDict
Author: Stefan Welcker
Author-email: stefan@u2d.ai
License: MIT
Project-URL: Documentation, http://msaStorageDict.u2d.ai/
Project-URL: Source, https://github.com/swelcker/msaStorageDict
Project-URL: Tracker, https://github.com/swelcker/msaStorageDict/issues
Classifier: Development Status :: 4 - Beta
Classifier: Framework :: FastAPI
Classifier: Intended Audience :: Developers
Classifier: License :: OSI Approved :: MIT License
Classifier: Operating System :: MacOS :: MacOS X
Classifier: Operating System :: Microsoft :: Windows
Classifier: Operating System :: POSIX :: Linux
Classifier: Programming Language :: Python :: 3
Classifier: Programming Language :: Python :: 3.7
Classifier: Programming Language :: Python :: 3.8
Classifier: Programming Language :: Python :: 3.9
Classifier: Programming Language :: Python :: 3.10
Classifier: Topic :: Database
Classifier: Topic :: Database :: Front-Ends
Classifier: Topic :: Documentation
Classifier: Topic :: Internet :: WWW/HTTP :: WSGI :: Server
Classifier: Topic :: Software Development :: Libraries
Classifier: Topic :: Software Development :: Libraries :: Python Modules
License-File: LICENCE
